uynab/__init__.py
uynab/__main__.py
uynab/client.py
uynab/config.py
uynab/error.py
uynab/py.typed
uynab/abstract/client.py
uynab/model/__init__.py
uynab/model/account.py
uynab/model/budget.py
uynab/model/category.py
uynab/model/payee.py
uynab/model/transaction.py
uynab/model/utils.py
uynab/service/__init__.py
uynab/service/account.py
uynab/service/budget.py
uynab/service/category.py
uynab/service/payee.py
uynab/service/service.py
uynab/service/transaction.py
uynab-0.1.5.dist-info/METADATA
uynab-0.1.5.dist-info/WHEEL
uynab-0.1.5.dist-info/licenses/LICENSE
uynab-0.1.5.dist-info/RECORD
