Metadata-Version: 2.4
Name: uynab
Version: 0.1.5
Summary: Micro YNAB - a small SDK for YNAB budgeting app
Project-URL: Documentation, https://ajwalkiewicz.github.io/uynab/
Project-URL: Repository, https://github.com/ajwalkiewicz/uynab
Project-URL: Issues, https://github.com/ajwalkiewicz/uynab/issues
Author-email: Adam Walkiewicz <aj.walkiewicz@gmail.com>
License-File: LICENSE
Keywords: API,SDK,YNAB,budget,money
Classifier: Development Status :: 4 - Beta
Classifier: Intended Audience :: Developers
Classifier: License :: OSI Approved :: MIT License
Classifier: Programming Language :: Python :: 3
Classifier: Programming Language :: Python :: 3.11
Classifier: Programming Language :: Python :: 3.12
Classifier: Programming Language :: Python :: 3.13
Requires-Python: >=3.11
Requires-Dist: click>=8.1.7
Requires-Dist: pydantic>=2.10.3
Requires-Dist: requests>=2.32.3
